pykmp/__init__.py
pykmp/client.py
pykmp/codec.py
pykmp/constants.py
pykmp/messages.py
pykmp/tool/__init__.py
pykmp/tool/__main__.py
PyKMP-0.0.1.dist-info/Apache-2.0.txt
PyKMP-0.0.1.dist-info/CC0-1.0.txt
PyKMP-0.0.1.dist-info/METADATA
PyKMP-0.0.1.dist-info/WHEEL
PyKMP-0.0.1.dist-info/entry_points.txt
PyKMP-0.0.1.dist-info/top_level.txt
PyKMP-0.0.1.dist-info/RECORD
