Metadata-Version: 2.1
Name: PyKMP
Version: 0.0.1
Summary: Library for the KMP protocol used with Kamstrup electricity/energy meters (e.g. MULTICAL® 30x/40x/60x).
Author-email: Gert van Dijk <github@gertvandijk.nl>
License: Apache License 2.0
Project-URL: homepage, https://github.com/gertvdijk/PyKMP
Project-URL: repository, https://github.com/gertvdijk/PyKMP.git
Classifier: Development Status :: 3 - Alpha
Classifier: License :: OSI Approved :: Apache Software License
Classifier: Programming Language :: Python :: 3
Classifier: Programming Language :: Python :: 3.10
Classifier: Programming Language :: Python :: 3.11
Classifier: Topic :: Software Development :: Libraries
Classifier: Typing :: Typed
Requires-Python: >=3.10
License-File: LICENSES/Apache-2.0.txt
License-File: LICENSES/CC0-1.0.txt
Requires-Dist: attrs
Requires-Dist: crc
Provides-Extra: development
Requires-Dist: black >=23.9.1 ; extra == 'development'
Requires-Dist: build ; extra == 'development'
Requires-Dist: check-wheel-contents ; extra == 'development'
Requires-Dist: click ; extra == 'development'
Requires-Dist: mock-serial ; extra == 'development'
Requires-Dist: mypy >=1.5.1 ; extra == 'development'
Requires-Dist: pyserial ; extra == 'development'
Requires-Dist: pytest-asyncio ; extra == 'development'
Requires-Dist: pytest-cov ; extra == 'development'
Requires-Dist: pytest ; extra == 'development'
Requires-Dist: reuse ; extra == 'development'
Requires-Dist: ruff >=0.0.291 ; extra == 'development'
Requires-Dist: setuptools-scm[toml] >=6.2 ; extra == 'development'
Requires-Dist: twine ; extra == 'development'
Requires-Dist: types-pyserial ; extra == 'development'
Requires-Dist: typing-extensions ; extra == 'development'
Requires-Dist: validate-pyproject[all] ; extra == 'development'
Provides-Extra: serial
Requires-Dist: pyserial ; extra == 'serial'
Provides-Extra: tool
Requires-Dist: click ; extra == 'tool'
Requires-Dist: pyserial ; extra == 'tool'
